dconvexhull/__init__.py
dconvexhull/operations/__init__.py
dconvexhull/operations/convhull.cp312-win_amd64.pyd
dconvexhull/operations/convxHull.py
dconvexhull/operations/graphConv.py
dconvexhull-0.1.3.dist-info/licenses/LICENSE
dconvexhull-0.1.3.dist-info/METADATA
dconvexhull-0.1.3.dist-info/WHEEL
dconvexhull-0.1.3.dist-info/top_level.txt
dconvexhull-0.1.3.dist-info/RECORD
