Metadata-Version: 2.4
Name: dconvexhull
Version: 0.1.3
Summary: Educational Python API wrapping a C++ convex hull module (2D only, outputs PDF visualization)
Home-page: https://github.com/dahmansphi/dconvexhull
Author: Deniz DAHMAN
Author-email: denizdahman@gmail.com
License: MIT
Classifier: Programming Language :: Python :: 3
Classifier: License :: OSI Approved :: MIT License
Classifier: Operating System :: OS Independent
Classifier: Intended Audience :: Education
Classifier: Topic :: Scientific/Engineering :: Mathematics
Requires-Python: >=3.8
License-File: LICENSE
Requires-Dist: matplotlib
Dynamic: license-file
